spaten/__init__.py
spaten/fileformat_pb2.py
spaten/spaten.py
spaten/test_spaten.py
spaten-0.4.1.dist-info/LICENSE
spaten-0.4.1.dist-info/METADATA
spaten-0.4.1.dist-info/WHEEL
spaten-0.4.1.dist-info/top_level.txt
spaten-0.4.1.dist-info/RECORD
