Metadata-Version: 2.1
Name: spaten
Version: 0.4.1
Summary: Spaten File Format Library
Home-page: https://github.com/thomersch/py-spaten
Author: Thomas Skowron
Author-email: th@skowron.eu
License: UNKNOWN
Platform: UNKNOWN
Classifier: Programming Language :: Python :: 3
Classifier: License :: OSI Approved :: Apache Software License
Classifier: Topic :: Scientific/Engineering :: GIS
Requires-Dist: Shapely
Requires-Dist: protobuf (>=3.0.0)
